pydantic_airtable/__init__.py
pydantic_airtable/base.py
pydantic_airtable/client.py
pydantic_airtable/config.py
pydantic_airtable/exceptions.py
pydantic_airtable/field_types.py
pydantic_airtable/fields.py
pydantic_airtable/http_client.py
pydantic_airtable/manager.py
pydantic_airtable/models.py
pydantic_airtable-1.0.1.dist-info/licenses/LICENSE
pydantic_airtable-1.0.1.dist-info/METADATA
pydantic_airtable-1.0.1.dist-info/WHEEL
pydantic_airtable-1.0.1.dist-info/top_level.txt
pydantic_airtable-1.0.1.dist-info/RECORD
