Metadata-Version: 2.4
Name: pydantic-airtable
Version: 1.0.1
Summary: A Python library for managing Airtable data using Pydantic objects
Home-page: https://github.com/grishick/pydantic-airtable
Author: Greg Solovyev
Author-email: Greg Solovyev <fiddlestring@gmail.com>
License-Expression: MIT
Project-URL: Homepage, https://github.com/grishick/pydantic-airtable
Project-URL: Documentation, https://pydantic-airtable.readthedocs.io/
Project-URL: Repository, https://github.com/grishick/pydantic-airtable
Project-URL: Issues, https://github.com/grishick/pydantic-airtable/issues
Keywords: airtable,pydantic,orm,api,database
Classifier: Development Status :: 4 - Beta
Classifier: Intended Audience :: Developers
Classifier: Operating System :: OS Independent
Classifier: Programming Language :: Python :: 3
Classifier: Programming Language :: Python :: 3.8
Classifier: Programming Language :: Python :: 3.9
Classifier: Programming Language :: Python :: 3.10
Classifier: Programming Language :: Python :: 3.11
Classifier: Programming Language :: Python :: 3.12
Classifier: Topic :: Database
Classifier: Topic :: Software Development :: Libraries :: Python Modules
Classifier: Typing :: Typed
Requires-Python: >=3.8
License-File: LICENSE
Requires-Dist: pydantic>=2.0.0
Requires-Dist: requests>=2.28.0
Provides-Extra: dev
Requires-Dist: pytest>=7.0.0; extra == "dev"
Requires-Dist: pytest-cov>=4.0.0; extra == "dev"
Requires-Dist: black>=23.0.0; extra == "dev"
Requires-Dist: isort>=5.12.0; extra == "dev"
Requires-Dist: mypy>=1.0.0; extra == "dev"
Provides-Extra: docs
Requires-Dist: mkdocs>=1.5.0; extra == "docs"
Requires-Dist: mkdocs-material>=9.0.0; extra == "docs"
Requires-Dist: mkdocstrings[python]>=0.24.0; extra == "docs"
Dynamic: author
Dynamic: home-page
Dynamic: license-file
Dynamic: requires-python
